techdata.py
techdatalibrary-0.0.1.dist-info/METADATA
techdatalibrary-0.0.1.dist-info/WHEEL
techdatalibrary-0.0.1.dist-info/top_level.txt
techdatalibrary-0.0.1.dist-info/RECORD
