Metadata-Version: 2.1
Name: techdatalibrary
Version: 0.0.1
Summary: Gathers tech data
Classifier: Programming Language :: Python :: 3.9
Classifier: Programming Language :: Python :: 3.10
Classifier: Programming Language :: Python :: 3.11
Classifier: Operating System :: OS Independent
Requires-Dist: pandas
Requires-Dist: mplfinance
